interpret_z/__init__.py
interpret_z/ast_z.py
interpret_z/const_z.py
interpret_z/interpret_z.py
interpret_z/parse_z.py
interpret_z/scan_z.py
interpret_z/test_integration.py
interpret_z/token_z.py
interpret_z-0.0.3.dist-info/DESCRIPTION.rst
interpret_z-0.0.3.dist-info/METADATA
interpret_z-0.0.3.dist-info/RECORD
interpret_z-0.0.3.dist-info/WHEEL
interpret_z-0.0.3.dist-info/metadata.json
interpret_z-0.0.3.dist-info/top_level.txt
